wifi_manager.py
micropython_wifimanager-1.0.2.dist-info/METADATA
micropython_wifimanager-1.0.2.dist-info/WHEEL
micropython_wifimanager-1.0.2.dist-info/top_level.txt
micropython_wifimanager-1.0.2.dist-info/RECORD
