Metadata-Version: 2.4
Name: micropython-wifimanager
Version: 1.0.2
Summary: A simple network configuration utility for MicroPython on the ESP-8266 and ESP-32 boards
Home-page: https://github.com/mitchins/micropython-wifimanager
Download-URL: https://github.com/mitchins/micropython-wifimanager/archive/1.0.1.tar.gz
Author: Mitchell Currie
Author-email: mitch@mitchellcurrie.com
Keywords: micropython,esp8266,esp32,wifi,manager
Dynamic: author
Dynamic: author-email
Dynamic: description
Dynamic: description-content-type
Dynamic: download-url
Dynamic: home-page
Dynamic: keywords
Dynamic: summary
